infi.pkgmgr-0.1.18-py3.7-nspkg.pth
infi/pkgmgr/__init__.py
infi/pkgmgr/__version__.py
infi/pkgmgr/tests.py
infi.pkgmgr-0.1.18.dist-info/LICENSE
infi.pkgmgr-0.1.18.dist-info/METADATA
infi.pkgmgr-0.1.18.dist-info/WHEEL
infi.pkgmgr-0.1.18.dist-info/entry_points.txt
infi.pkgmgr-0.1.18.dist-info/namespace_packages.txt
infi.pkgmgr-0.1.18.dist-info/top_level.txt
infi.pkgmgr-0.1.18.dist-info/RECORD
